orgblog
