Metadata-Version: 1.0
Name: orgblog
Version: 0.7.6
Summary: easy web publishing with org-mode files
Home-page: http://github.com/ctindall/org-blog
Author: Cameron Tindall
Author-email: cam@tindall.space
License: GPL
Platform: UNKNOWN
